dash_blueprints/__init__.py
dash_blueprints/ag_common.py
dash_blueprints/aio/__init__.py
dash_blueprints/aio/ag_grid.py
dash_blueprints/aio/base.py
dash_blueprints/aio/dropdown_checkbox.py
dash_blueprints/aio/favourites.py
dash_blueprints/assets/ag_react.js
dash_blueprints/assets/common.css
dash_blueprints/dynamic_callbacks.py
dash_blueprints/examples/__init__.py
dash_blueprints/examples/ag_grid.py
dash_blueprints/examples/ag_grid_0.py
dash_blueprints/examples/assets/common.css
dash_blueprints/examples/file_system_backend/0ada43744fd89c05464a41b4a62ea74d
dash_blueprints/examples/file_system_backend/1bfb4611ed4acb6d54cf66d150c1b27c
dash_blueprints/examples/file_system_backend/1c0df87983be64a84d3203dc1ae8f16e
dash_blueprints/examples/file_system_backend/1f3ff5b00a9257dd9fc1395ac848ba26
dash_blueprints/examples/file_system_backend/2029240f6d1128be89ddc32729463129
dash_blueprints/examples/file_system_backend/2ce365d3fc44434eab1e9c8544af78e1
dash_blueprints/examples/file_system_backend/5b136cca1799409dc8f637bbdc774492
dash_blueprints/examples/file_system_backend/b395c8fd0f53dbfcbfd7a581158d22a7
dash_blueprints/examples/file_system_backend/e0e3fa7cfa92523a0ea2b4f60fd169d1
dash_blueprints/examples/file_system_backend/fefb37a6cfd392e34521dddf676b31b7
dash_blueprints/utils.py
dash_blueprints-0.1.5.dist-info/LICENSE
dash_blueprints-0.1.5.dist-info/METADATA
dash_blueprints-0.1.5.dist-info/WHEEL
dash_blueprints-0.1.5.dist-info/RECORD
